LICENSE
README.md
b2.json
setup.cfg
setup.py
b2/__init__.py
b2/b2.py
b2/b2_magic.py
b2/config.py
b2/constants.py
b2/context_types.py
b2/showme.py
b2/state_types.py
b2/ui_comm.py
b2/vis_types.py
b2/algebra/__init__.py
b2/algebra/context.py
b2/algebra/data_types.py
b2/algebra/dataframe.py
b2/algebra/selection.py
b2/static/__init__.py
b2/static/index.js
b2/static/index.js.map
b2/static/showme.py
b2/tests_old/__init__.py
b2/tests_old/all.py
b2/tests_old/test_rendering.py
b2/tests_old/test_util.py
b2/util/__init__.py
b2/util/data_processing.py
b2/util/errors.py
b2/util/instructions.py
b2/util/utils.py
b2_ext.egg-info/PKG-INFO
b2_ext.egg-info/SOURCES.txt
b2_ext.egg-info/dependency_links.txt
b2_ext.egg-info/top_level.txt