Metadata-Version: 1.1
Name: b2-ext
Version: 0.0.5
Summary: B2: easy EDA in Jupyter Notebook
Home-page: http://github.com/yifanwu/b2
Author: Yifan Wu
Author-email: yifanwu@berkeley.edu
License: BSD 3-clause
Download-URL: http://github.com/yifanwu/b2
Platform: UNKNOWN
Classifier: Development Status :: 2 - Pre-Alpha
Classifier: Environment :: Other Environment
Classifier: Intended Audience :: Science/Research
Classifier: License :: OSI Approved :: Apache Software License
Classifier: Natural Language :: English
Classifier: Programming Language :: Python
Classifier: Programming Language :: Python :: 3.7
